{  "type": "FeatureCollection", "name": "map1_breaker", "crs": { "type": "name", "properties": { "name": "urn:ogc:def:crs:OGC:1.3:CRS84" } }, "features": [
{ "type": "Feature",  "properties": {  "JAEDType": "RelayBreaker", "Breaker ID": "OCR123.891872709582000-11.071040668640700", "Prot. Section ID": "SUBTR-HVPole-123.869549559364000-11.062899284443600_HVPole-123.905791850306000-11.077081050464400", "Phase": "ABCN", "Size": "2500", "Location": "", "Brand": "ABB", "Model": "REF543M", "Type": "Extremely inverse IEC", "KVRating": "72.5"}, "geometry": {  "type": "Point",  "coordinates": [ 123.891872709581, 11.0710406686407 ]  } }
]}
