{  "type": "FeatureCollection", "name": "map1_avr", "crs": { "type": "name", "properties": { "name": "urn:ogc:def:crs:OGC:1.3:CRS84" } }, "features": [
{ "type": "Feature",  "properties": {  "JAEDType": "AVR", "AVR ID": "AVR-123.857206170420000-11.054232649653100", "FromBus": "AVR-123.857206170420000-11.054232649653100PRI", "ToBus": "AVR-123.857206170420000-11.054232649653100SEC", "Phase": "ABCN", "KVA Rating": "250", "Brand": "", "Model": "", "Serial": ""}, "geometry": {  "type": "Point",  "coordinates": [ 123.857206170419, 11.0542326496531 ]  } }
]}
